[
   {
      "name": "AI Engineer",
      "career": [
         "AI Engineer",
         "Artificial Intelligence Engineer",
         "Machine Learning Engineer",
         "Machine Learning Engineering"
      ],
      "people": [],
      "count": 0
   },
   {
      "name": "Big Data Engineer",
      "career": [
         "Big Data Engineer",
         "Big Data Architect",
         "Big Data Developer",
         "Big Data Analyst",
         "Big Data Administrator"
      ],
      "people": [],
      "count": 0
   },
   {
      "name": "Cloud Architect",
      "career": [
         "Cloud Architect"
      ],
      "people": [],
      "count": 0
   },
   {
      "name": "Computer Hardware Engineer",
      "career": [
         "Computer Hardware Engineer"
      ],
      "people": [],
      "count": 0
   },
   {
      "name": "Data Analyst",
      "career": [
         "Data Analyst",
         "Data Specialist",
         "Business Data Analyst",
         "Data Consultant",
         "Data Technician",
         "Data Abstractor"
      ],
      "people": [
         {
            "name": "Muhammad Nurharianto",
            "weight": 6
         }
      ],
      "count": 1
   },
   {
      "name": "Data Architect",
      "career": [
         "Data Architect",
         "Information Architect",
         "Database Architect",
         "Business Intelligence Architect",
         "BI Architect",
         "Data Warehouse Architect"
      ],
      "people": [
         {
            "name": "Misdan Wijaya",
            "weight": 22
         }
      ],
      "count": 1
   },
   {
      "name": "Data Engineer",
      "career": [
         "Data Engineer",
         "Data Administrator",
         "Data Modeler",
         "Data Developer"
      ],
      "people": [
         {
            "name": "Muhammad Nurharianto",
            "weight": 19
         },
         {
            "name": "Misdan Wijaya",
            "weight": 12
         }
      ],
      "count": 2
   },
   {
      "name": "Data Scientist",
      "career": [
         "Data Scientist",
         "Data Analytics Analyst",
         "Data Analytics Specialist"
      ],
      "people": [],
      "count": 0
   },
   {
      "name": "Database Administrator",
      "career": [
         "Database Administrator",
         "DBA",
         "Database Manager",
         "Data Administrator",
         "Database Admin",
         "Database DBA"
      ],
      "people": [],
      "count": 0
   },
   {
      "name": "Database Developer",
      "career": [
         "Database Developer",
         "Database Engineer",
         "Database Programmer",
         "Database Management Developer"
      ],
      "people": [
         {
            "name": "Muhammad Nurharianto",
            "weight": 13
         },
         {
            "name": "Haris Hidayat",
            "weight": 13
         }
      ],
      "count": 2
   },
   {
      "name": "Graphic Designer",
      "career": [
         "Graphic Designer",
         "3D Modeler",
         "3D Developer"
      ],
      "people": [
         {
            "name": "Anastasya Reskianissa",
            "weight": 58
         },
         {
            "name": "Muhammad Nadzir Azhar",
            "weight": 24
         },
         {
            "name": "Masyita I.",
            "weight": 23
         },
         {
            "name": "Muhammad Rheza Alvarez Satriadipura",
            "weight": 3
         },
         {
            "name": "Rizal Purnomo",
            "weight": 3
         },
         {
            "name": "Gunawan Busyaeri",
            "weight": 0
         }
      ],
      "count": 6
   },
   {
      "name": "Information Security Analyst",
      "career": [
         "Information Security Analyst",
         "Security Analyst",
         "IT Security Analyst",
         "Cyber Security Analyst",
         "Information Security Specialist",
         "Cyber Security Specialist"
      ],
      "people": [],
      "count": 0
   },
   {
      "name": "Programmer",
      "career": [
         "Programmer"
      ],
      "people": [
         {
            "name": "Fahmi Salfiyari",
            "weight": 12
         },
         {
            "name": "Misdan Wijaya",
            "weight": 12
         },
         {
            "name": "Muhamad Habib Ibnu H.",
            "weight": 3
         },
         {
            "name": "Reyhan Fikri Dzikriansyah",
            "weight": 2
         }
      ],
      "count": 4
   },
   {
      "name": "Software Engineer",
      "career": [
         "Software Engineer",
         "Software Developer",
         "Application Developer",
         "Application Engineer",
         "Programmer Analyst",
         "Software Development Engineer",
         "Mobile Developer",
         "IT Developer"
      ],
      "people": [
         {
            "name": "Hadian Mutakin",
            "weight": 51
         },
         {
            "name": "Dina Dwi Handayani",
            "weight": 32
         },
         {
            "name": "Dian Lazuardi",
            "weight": 32
         },
         {
            "name": "Reyhan Fikri Dzikriansyah",
            "weight": 31
         },
         {
            "name": "Anastasya Reskianissa",
            "weight": 23
         },
         {
            "name": "Haris Hidayat",
            "weight": 20
         },
         {
            "name": "Ramdan Syaripudin",
            "weight": 18
         },
         {
            "name": "Muhammad Rheza Alvarez Satriadipura",
            "weight": 10
         },
         {
            "name": "Wahyu Tricahyo",
            "weight": 7
         },
         {
            "name": "Irfan Muhammad Faisal",
            "weight": 5
         },
         {
            "name": "Reihan Manzis Syahputra",
            "weight": 4
         },
         {
            "name": "Misdan Wijaya",
            "weight": 3
         },
         {
            "name": "Rizal Purnomo",
            "weight": 1
         }
      ],
      "count": 13
   },
   {
      "name": "UI Designer",
      "career": [
         "UI Designer",
         "User Interface Designer",
         "Visual Designer",
         "UI Strategist",
         "UI Innovator",
         "Content Strategist",
         "UI/UX Designer"
      ],
      "people": [
         {
            "name": "Masyita I.",
            "weight": 16
         },
         {
            "name": "Ramdan Syaripudin",
            "weight": 12
         },
         {
            "name": "Gunawan Busyaeri",
            "weight": 0
         }
      ],
      "count": 3
   },
   {
      "name": "UX Designer",
      "career": [
         "UX Designer",
         "User Experience Designer",
         "UX Researcher",
         "UX Architect",
         "Interaction Designer",
         "Experience Designer",
         "UI/UX Designer"
      ],
      "people": [
         {
            "name": "Masyita I.",
            "weight": 16
         },
         {
            "name": "Ramdan Syaripudin",
            "weight": 6
         },
         {
            "name": "Gunawan Busyaeri",
            "weight": 0
         }
      ],
      "count": 3
   },
   {
      "name": "Web Developer",
      "career": [
         "Web Developer",
         "Front End Developer",
         "Front End Web Developer",
         "Frontend Developer",
         "Web Designer",
         "Web Application Developer",
         "Front End Engineer",
         "Frontend Engineer",
         "Website Designer",
         "Website Developer",
         "Back End Developer",
         "Backend Developer",
         "Web Programmer",
         "Full Stack Engineer",
         "Full-Stack Engineer",
         "Full-Stack Developer"
      ],
      "people": [
         {
            "name": "Wiwi Juwita",
            "weight": 79
         },
         {
            "name": "Dian Lazuardi",
            "weight": 70
         },
         {
            "name": "Rizki Nugraha",
            "weight": 70
         },
         {
            "name": "Rizal Purnomo",
            "weight": 59
         },
         {
            "name": "Wahyu Tricahyo",
            "weight": 51
         },
         {
            "name": "Jaka Septiadi",
            "weight": 44
         },
         {
            "name": "Chandra Muhamad Apriana",
            "weight": 39
         },
         {
            "name": "Fathurrachman Damar Saputra",
            "weight": 38
         },
         {
            "name": "Misdan Wijaya",
            "weight": 36
         },
         {
            "name": "Deffin Achmaddifa",
            "weight": 23
         },
         {
            "name": "Reyhan Fikri Dzikriansyah",
            "weight": 20
         },
         {
            "name": "Reihan Manzis Syahputra",
            "weight": 20
         },
         {
            "name": "Muhammad Nur Ilman",
            "weight": 18
         },
         {
            "name": "Haris Hidayat",
            "weight": 12
         },
         {
            "name": "Fahmi Salfiyari",
            "weight": 12
         },
         {
            "name": "Dina Dwi Handayani",
            "weight": 6
         },
         {
            "name": "Hasya Ghitha",
            "weight": 5
         },
         {
            "name": "Muhammad Rheza Alvarez Satriadipura",
            "weight": 2
         }
      ],
      "count": 18
   },
   {
      "name": "Other",
      "career": [],
      "people": [
         {
            "name": "Agung Hari Pramono",
            "weight": 0
         },
         {
            "name": "arief (rahman) Ibrahim",
            "weight": 0
         },
         {
            "name": "Arvian Triantoro",
            "weight": 0
         },
         {
            "name": "Cinta Delvianne",
            "weight": 0
         },
         {
            "name": "Cynthia Calista Jaya",
            "weight": 0
         },
         {
            "name": "Davina Cherryl Aurelia",
            "weight": 0
         },
         {
            "name": "Denisya Nurul Azizah",
            "weight": 0
         },
         {
            "name": "Dieke Husna Kamilla",
            "weight": 0
         },
         {
            "name": "Dimas Handi",
            "weight": 0
         },
         {
            "name": "Elma Liawati",
            "weight": 0
         },
         {
            "name": "Fatih Izzul Haq",
            "weight": 0
         },
         {
            "name": "Fatin Fauziyyah Tiras Putri",
            "weight": 0
         },
         {
            "name": "Fauzi Nur",
            "weight": 0
         },
         {
            "name": "Febrinita Putri Sumiharto",
            "weight": 0
         },
         {
            "name": "Gina Istiqomah",
            "weight": 0
         },
         {
            "name": "Hanif Syafrian Purnama",
            "weight": 0
         },
         {
            "name": "Hardian Ari Yoga Putra",
            "weight": 0
         },
         {
            "name": "Hardiansah Faisal Rito",
            "weight": 0
         },
         {
            "name": "Irmadel Aurelliana",
            "weight": 0
         },
         {
            "name": "Isman Rahmani",
            "weight": 0
         },
         {
            "name": "K. Moh Lutfi Hamdani",
            "weight": 0
         },
         {
            "name": "Karina Permata",
            "weight": 0
         },
         {
            "name": "Khusnul Dwi Nurfalah",
            "weight": 0
         },
         {
            "name": "LUSI PEBRIANI",
            "weight": 0
         },
         {
            "name": "Mahyati -",
            "weight": 0
         },
         {
            "name": "Marisa K.",
            "weight": 0
         },
         {
            "name": "Mega Cahya Pratiwi",
            "weight": 0
         },
         {
            "name": "Muhamad Gibran Mauludin",
            "weight": 0
         },
         {
            "name": "Muhamad Raihan Taqwa",
            "weight": 0
         },
         {
            "name": "Muhammad Kautsar",
            "weight": 0
         },
         {
            "name": "Mutiara Shafira Hikmanudin",
            "weight": 0
         },
         {
            "name": "Nadissa Qirshani Rahman",
            "weight": 0
         },
         {
            "name": "Neng Nurhasanah",
            "weight": 0
         },
         {
            "name": "Purnama Muntaharridwan",
            "weight": 0
         },
         {
            "name": "Putri Nurwaqiah",
            "weight": 0
         },
         {
            "name": "Rani Megasari",
            "weight": 0
         },
         {
            "name": "Rhena Indria Haryono",
            "weight": 0
         },
         {
            "name": "Rita Haryati",
            "weight": 0
         },
         {
            "name": "Rizky Lukman Hakim",
            "weight": 0
         },
         {
            "name": "Salma Hanifah",
            "weight": 0
         },
         {
            "name": "Salsabila Fitri Pratami",
            "weight": 0
         },
         {
            "name": "Shafira Widihardjo",
            "weight": 0
         },
         {
            "name": "Sifa Marcella Fardhani",
            "weight": 0
         },
         {
            "name": "Siti Sofia Hanum",
            "weight": 0
         },
         {
            "name": "Syifa Kudiarto",
            "weight": 0
         },
         {
            "name": "Tasya Prillia Purnama",
            "weight": 0
         },
         {
            "name": "uga nugraha syafari",
            "weight": 0
         },
         {
            "name": "Vina Anggraeni",
            "weight": 0
         }
      ],
      "count": 48
   }
]